fnug-0.0.27.dist-info/METADATA
fnug-0.0.27.dist-info/WHEEL
fnug-0.0.27.dist-info/entry_points.txt
fnug-0.0.27.dist-info/licenses/LICENSE
fnug/cli.py
fnug/core.pyi
fnug/logging.py
fnug/ui/app.py
fnug/ui/app.tcss
fnug/ui/components/context_menu.py
fnug/ui/components/context_menu.tcss
fnug/ui/components/lint_tree.py
fnug/ui/components/terminal.py
fnug/ui/components/__init__.py
fnug/ui/__init__.py
fnug/__init__.py
fnug/__main__.py
fnug/core.pyd
fnug-0.0.27.dist-info/RECORD
