Metadata-Version: 2.4
Name: fnug
Version: 0.0.27
Classifier: Development Status :: 3 - Alpha
Classifier: Intended Audience :: Developers
Classifier: Environment :: Console
Classifier: Environment :: Console :: Curses
Classifier: Intended Audience :: Developers
Classifier: Topic :: Software Development :: Build Tools
Classifier: Topic :: Software Development :: Testing
Classifier: Topic :: Terminals :: Terminal Emulators/X Terminals
Classifier: License :: OSI Approved :: GNU General Public License v3 (GPLv3)
Classifier: Programming Language :: Python :: 3
Classifier: Programming Language :: Python :: 3.10
Classifier: Programming Language :: Python :: 3.11
Classifier: Programming Language :: Python :: 3.12
Requires-Dist: click >=8.1.7
Requires-Dist: textual >=0.85.2
Requires-Dist: rich >=13.9.2
Requires-Dist: pydantic >=2.7.1
Requires-Dist: click-default-group >=1.2.4
License-File: LICENSE
Summary: A nice lint runner
Author-email: Nickolaj Jepsen <nickolaj@fireproof.website>
License: GPL-3.0
Requires-Python: >=3.10
Project-URL: Repository, https://github.com/nickolaj-jepsen/fnug.git
Project-URL: Issues, https://github.com/nickolaj-jepsen/fnug/issues
